{
    "schemes": [
        "http"
    ],
    "swagger": "2.0",
    "info": {
        "description": "SneakerFlash 球鞋秒杀系统接口文档",
        "title": "SneakerFlash API",
        "contact": {},
        "version": "1.0"
    },
    "basePath": "/api/v1",
    "paths": {
        "/coupons/mine": {
            "get": {
                "security": [
                    {
                        "BearerAuth": []
                    }
                ],
                "produces": [
                    "application/json"
                ],
                "tags": [
                    "Coupon"
                ],
                "summary": "我的优惠券",
                "parameters": [
                    {
                        "type": "string",
                        "description": "available/used/expired",
                        "name": "status",
                        "in": "query"
                    }
                ],
                "responses": {
                    "200": {
                        "description": "OK",
                        "schema": {
                            "allOf": [
                                {
                                    "$ref": "#/definitions/app.Response"
                                },
                                {
                                    "type": "object",
                                    "properties": {
                                        "data": {
                                            "type": "array",
                                            "items": {
                                                "$ref": "#/definitions/service.MyCoupon"
                                            }
                                        }
                                    }
                                }
                            ]
                        }
                    }
                }
            }
        },
        "/coupons/purchase": {
            "post": {
                "security": [
                    {
                        "BearerAuth": []
                    }
                ],
                "consumes": [
                    "application/json"
                ],
                "produces": [
                    "application/json"
                ],
                "tags": [
                    "Coupon"
                ],
                "summary": "购买优惠券（模拟支付）",
                "parameters": [
                    {
                        "description": "coupon_id",
                        "name": "payload",
                        "in": "body",
                        "required": true,
                        "schema": {
                            "$ref": "#/definitions/handler.PurchaseCouponReq"
                        }
                    }
                ],
                "responses": {
                    "200": {
                        "description": "OK",
                        "schema": {
                            "allOf": [
                                {
                                    "$ref": "#/definitions/app.Response"
                                },
                                {
                                    "type": "object",
                                    "properties": {
                                        "data": {
                                            "$ref": "#/definitions/service.MyCoupon"
                                        }
                                    }
                                }
                            ]
                        }
                    }
                }
            }
        },
        "/login": {
            "post": {
                "description": "登录后下发 access/refresh token",
                "consumes": [
                    "application/json"
                ],
                "produces": [
                    "application/json"
                ],
                "tags": [
                    "用户"
                ],
                "summary": "用户登录",
                "parameters": [
                    {
                        "description": "登录信息",
                        "name": "payload",
                        "in": "body",
                        "required": true,
                        "schema": {
                            "$ref": "#/definitions/handler.RegisterReq"
                        }
                    }
                ],
                "responses": {
                    "200": {
                        "description": "OK",
                        "schema": {
                            "allOf": [
                                {
                                    "$ref": "#/definitions/app.Response"
                                },
                                {
                                    "type": "object",
                                    "properties": {
                                        "data": {
                                            "$ref": "#/definitions/handler.TokenPairResponse"
                                        }
                                    }
                                }
                            ]
                        }
                    },
                    "400": {
                        "description": "参数错误",
                        "schema": {
                            "$ref": "#/definitions/app.Response"
                        }
                    },
                    "401": {
                        "description": "认证失败",
                        "schema": {
                            "$ref": "#/definitions/app.Response"
                        }
                    }
                }
            }
        },
        "/orders": {
            "get": {
                "security": [
                    {
                        "BearerAuth": []
                    }
                ],
                "produces": [
                    "application/json"
                ],
                "tags": [
                    "订单"
                ],
                "summary": "查询订单列表",
                "parameters": [
                    {
                        "type": "integer",
                        "default": 1,
                        "description": "页码",
                        "name": "page",
                        "in": "query"
                    },
                    {
                        "type": "integer",
                        "default": 10,
                        "description": "每页条数",
                        "name": "size",
                        "in": "query"
                    },
                    {
                        "type": "integer",
                        "description": "订单状态：0未支付 1已支付 2失败",
                        "name": "status",
                        "in": "query"
                    }
                ],
                "responses": {
                    "200": {
                        "description": "OK",
                        "schema": {
                            "allOf": [
                                {
                                    "$ref": "#/definitions/app.Response"
                                },
                                {
                                    "type": "object",
                                    "properties": {
                                        "data": {
                                            "$ref": "#/definitions/handler.OrderListResponse"
                                        }
                                    }
                                }
                            ]
                        }
                    },
                    "400": {
                        "description": "参数错误",
                        "schema": {
                            "$ref": "#/definitions/app.Response"
                        }
                    },
                    "401": {
                        "description": "未登录",
                        "schema": {
                            "$ref": "#/definitions/app.Response"
                        }
                    }
                }
            },
            "post": {
                "security": [
                    {
                        "BearerAuth": []
                    }
                ],
                "consumes": [
                    "application/json"
                ],
                "produces": [
                    "application/json"
                ],
                "tags": [
                    "订单"
                ],
                "summary": "创建订单并初始化支付",
                "parameters": [
                    {
                        "description": "订单参数（可选 coupon_id）",
                        "name": "payload",
                        "in": "body",
                        "required": true,
                        "schema": {
                            "$ref": "#/definitions/handler.CreateOrderReq"
                        }
                    }
                ],
                "responses": {
                    "200": {
                        "description": "OK",
                        "schema": {
                            "allOf": [
                                {
                                    "$ref": "#/definitions/app.Response"
                                },
                                {
                                    "type": "object",
                                    "properties": {
                                        "data": {
                                            "$ref": "#/definitions/handler.OrderWithPaymentResponse"
                                        }
                                    }
                                }
                            ]
                        }
                    },
                    "400": {
                        "description": "参数错误",
                        "schema": {
                            "$ref": "#/definitions/app.Response"
                        }
                    },
                    "401": {
                        "description": "未登录",
                        "schema": {
                            "$ref": "#/definitions/app.Response"
                        }
                    },
                    "404": {
                        "description": "商品不存在",
                        "schema": {
                            "$ref": "#/definitions/app.Response"
                        }
                    }
                }
            }
        },
        "/orders/{id}": {
            "get": {
                "security": [
                    {
                        "BearerAuth": []
                    }
                ],
                "produces": [
                    "application/json"
                ],
                "tags": [
                    "订单"
                ],
                "summary": "获取订单详情",
                "parameters": [
                    {
                        "type": "integer",
                        "description": "订单ID",
                        "name": "id",
                        "in": "path",
                        "required": true
                    }
                ],
                "responses": {
                    "200": {
                        "description": "OK",
                        "schema": {
                            "allOf": [
                                {
                                    "$ref": "#/definitions/app.Response"
                                },
                                {
                                    "type": "object",
                                    "properties": {
                                        "data": {
                                            "$ref": "#/definitions/handler.OrderWithPaymentResponse"
                                        }
                                    }
                                }
                            ]
                        }
                    },
                    "400": {
                        "description": "参数错误",
                        "schema": {
                            "$ref": "#/definitions/app.Response"
                        }
                    },
                    "401": {
                        "description": "未登录",
                        "schema": {
                            "$ref": "#/definitions/app.Response"
                        }
                    },
                    "404": {
                        "description": "未找到",
                        "schema": {
                            "$ref": "#/definitions/app.Response"
                        }
                    }
                }
            }
        },
        "/payment/callback": {
            "post": {
                "consumes": [
                    "application/json"
                ],
                "produces": [
                    "application/json"
                ],
                "tags": [
                    "订单"
                ],
                "summary": "支付回调",
                "parameters": [
                    {
                        "description": "支付回调参数",
                        "name": "payload",
                        "in": "body",
                        "required": true,
                        "schema": {
                            "$ref": "#/definitions/handler.PaymentCallbackReq"
                        }
                    }
                ],
                "responses": {
                    "200": {
                        "description": "OK",
                        "schema": {
                            "allOf": [
                                {
                                    "$ref": "#/definitions/app.Response"
                                },
                                {
                                    "type": "object",
                                    "properties": {
                                        "data": {
                                            "$ref": "#/definitions/handler.OrderWithPaymentResponse"
                                        }
                                    }
                                }
                            ]
                        }
                    },
                    "400": {
                        "description": "参数错误",
                        "schema": {
                            "$ref": "#/definitions/app.Response"
                        }
                    },
                    "404": {
                        "description": "支付单不存在",
                        "schema": {
                            "$ref": "#/definitions/app.Response"
                        }
                    }
                }
            }
        },
        "/product/{id}": {
            "get": {
                "produces": [
                    "application/json"
                ],
                "tags": [
                    "商品"
                ],
                "summary": "获取商品详情",
                "parameters": [
                    {
                        "type": "integer",
                        "description": "商品ID",
                        "name": "id",
                        "in": "path",
                        "required": true
                    }
                ],
                "responses": {
                    "200": {
                        "description": "OK",
                        "schema": {
                            "allOf": [
                                {
                                    "$ref": "#/definitions/app.Response"
                                },
                                {
                                    "type": "object",
                                    "properties": {
                                        "data": {
                                            "$ref": "#/definitions/model.Product"
                                        }
                                    }
                                }
                            ]
                        }
                    },
                    "400": {
                        "description": "参数错误",
                        "schema": {
                            "$ref": "#/definitions/app.Response"
                        }
                    },
                    "404": {
                        "description": "未找到",
                        "schema": {
                            "$ref": "#/definitions/app.Response"
                        }
                    }
                }
            }
        },
        "/products": {
            "get": {
                "produces": [
                    "application/json"
                ],
                "tags": [
                    "商品"
                ],
                "summary": "获取商品列表",
                "parameters": [
                    {
                        "type": "integer",
                        "default": 1,
                        "description": "页码",
                        "name": "page",
                        "in": "query"
                    },
                    {
                        "type": "integer",
                        "default": 10,
                        "description": "每页条数",
                        "name": "size",
                        "in": "query"
                    }
                ],
                "responses": {
                    "200": {
                        "description": "OK",
                        "schema": {
                            "allOf": [
                                {
                                    "$ref": "#/definitions/app.Response"
                                },
                                {
                                    "type": "object",
                                    "properties": {
                                        "data": {
                                            "$ref": "#/definitions/handler.ProductListResponse"
                                        }
                                    }
                                }
                            ]
                        }
                    },
                    "400": {
                        "description": "参数错误",
                        "schema": {
                            "$ref": "#/definitions/app.Response"
                        }
                    }
                }
            },
            "post": {
                "security": [
                    {
                        "BearerAuth": []
                    }
                ],
                "consumes": [
                    "application/json"
                ],
                "produces": [
                    "application/json"
                ],
                "tags": [
                    "商品"
                ],
                "summary": "发布商品",
                "parameters": [
                    {
                        "description": "商品参数",
                        "name": "payload",
                        "in": "body",
                        "required": true,
                        "schema": {
                            "$ref": "#/definitions/handler.CreateProductReq"
                        }
                    }
                ],
                "responses": {
                    "200": {
                        "description": "OK",
                        "schema": {
                            "allOf": [
                                {
                                    "$ref": "#/definitions/app.Response"
                                },
                                {
                                    "type": "object",
                                    "properties": {
                                        "data": {
                                            "$ref": "#/definitions/model.Product"
                                        }
                                    }
                                }
                            ]
                        }
                    },
                    "400": {
                        "description": "参数错误",
                        "schema": {
                            "$ref": "#/definitions/app.Response"
                        }
                    },
                    "401": {
                        "description": "未登录",
                        "schema": {
                            "$ref": "#/definitions/app.Response"
                        }
                    }
                }
            }
        },
        "/products/mine": {
            "get": {
                "security": [
                    {
                        "BearerAuth": []
                    }
                ],
                "produces": [
                    "application/json"
                ],
                "tags": [
                    "商品"
                ],
                "summary": "我的商品列表",
                "parameters": [
                    {
                        "type": "integer",
                        "default": 1,
                        "description": "页码",
                        "name": "page",
                        "in": "query"
                    },
                    {
                        "type": "integer",
                        "default": 10,
                        "description": "每页条数",
                        "name": "size",
                        "in": "query"
                    }
                ],
                "responses": {
                    "200": {
                        "description": "OK",
                        "schema": {
                            "allOf": [
                                {
                                    "$ref": "#/definitions/app.Response"
                                },
                                {
                                    "type": "object",
                                    "properties": {
                                        "data": {
                                            "$ref": "#/definitions/handler.ProductListWithSizeResponse"
                                        }
                                    }
                                }
                            ]
                        }
                    },
                    "400": {
                        "description": "参数错误",
                        "schema": {
                            "$ref": "#/definitions/app.Response"
                        }
                    },
                    "401": {
                        "description": "未登录",
                        "schema": {
                            "$ref": "#/definitions/app.Response"
                        }
                    }
                }
            }
        },
        "/products/{id}": {
            "put": {
                "security": [
                    {
                        "BearerAuth": []
                    }
                ],
                "consumes": [
                    "application/json"
                ],
                "produces": [
                    "application/json"
                ],
                "tags": [
                    "商品"
                ],
                "summary": "更新商品",
                "parameters": [
                    {
                        "type": "integer",
                        "description": "商品ID",
                        "name": "id",
                        "in": "path",
                        "required": true
                    },
                    {
                        "description": "商品参数",
                        "name": "payload",
                        "in": "body",
                        "required": true,
                        "schema": {
                            "$ref": "#/definitions/handler.UpdateProductReq"
                        }
                    }
                ],
                "responses": {
                    "200": {
                        "description": "OK",
                        "schema": {
                            "allOf": [
                                {
                                    "$ref": "#/definitions/app.Response"
                                },
                                {
                                    "type": "object",
                                    "properties": {
                                        "data": {
                                            "$ref": "#/definitions/handler.IDResponse"
                                        }
                                    }
                                }
                            ]
                        }
                    },
                    "400": {
                        "description": "参数错误",
                        "schema": {
                            "$ref": "#/definitions/app.Response"
                        }
                    },
                    "401": {
                        "description": "未登录",
                        "schema": {
                            "$ref": "#/definitions/app.Response"
                        }
                    },
                    "404": {
                        "description": "未找到",
                        "schema": {
                            "$ref": "#/definitions/app.Response"
                        }
                    }
                }
            },
            "delete": {
                "security": [
                    {
                        "BearerAuth": []
                    }
                ],
                "produces": [
                    "application/json"
                ],
                "tags": [
                    "商品"
                ],
                "summary": "删除商品",
                "parameters": [
                    {
                        "type": "integer",
                        "description": "商品ID",
                        "name": "id",
                        "in": "path",
                        "required": true
                    }
                ],
                "responses": {
                    "200": {
                        "description": "OK",
                        "schema": {
                            "allOf": [
                                {
                                    "$ref": "#/definitions/app.Response"
                                },
                                {
                                    "type": "object",
                                    "properties": {
                                        "data": {
                                            "$ref": "#/definitions/handler.IDResponse"
                                        }
                                    }
                                }
                            ]
                        }
                    },
                    "400": {
                        "description": "参数错误",
                        "schema": {
                            "$ref": "#/definitions/app.Response"
                        }
                    },
                    "401": {
                        "description": "未登录",
                        "schema": {
                            "$ref": "#/definitions/app.Response"
                        }
                    },
                    "404": {
                        "description": "未找到",
                        "schema": {
                            "$ref": "#/definitions/app.Response"
                        }
                    }
                }
            }
        },
        "/profile": {
            "get": {
                "security": [
                    {
                        "BearerAuth": []
                    }
                ],
                "produces": [
                    "application/json"
                ],
                "tags": [
                    "用户"
                ],
                "summary": "获取当前用户信息",
                "responses": {
                    "200": {
                        "description": "OK",
                        "schema": {
                            "allOf": [
                                {
                                    "$ref": "#/definitions/app.Response"
                                },
                                {
                                    "type": "object",
                                    "properties": {
                                        "data": {
                                            "$ref": "#/definitions/handler.UserResponse"
                                        }
                                    }
                                }
                            ]
                        }
                    },
                    "401": {
                        "description": "未登录",
                        "schema": {
                            "$ref": "#/definitions/app.Response"
                        }
                    }
                }
            },
            "put": {
                "security": [
                    {
                        "BearerAuth": []
                    }
                ],
                "consumes": [
                    "application/json"
                ],
                "produces": [
                    "application/json"
                ],
                "tags": [
                    "用户"
                ],
                "summary": "更新当前用户信息",
                "parameters": [
                    {
                        "description": "支持部分字段",
                        "name": "payload",
                        "in": "body",
                        "required": true,
                        "schema": {
                            "$ref": "#/definitions/handler.UpdateProfileReq"
                        }
                    }
                ],
                "responses": {
                    "200": {
                        "description": "OK",
                        "schema": {
                            "allOf": [
                                {
                                    "$ref": "#/definitions/app.Response"
                                },
                                {
                                    "type": "object",
                                    "properties": {
                                        "data": {
                                            "$ref": "#/definitions/handler.UserResponse"
                                        }
                                    }
                                }
                            ]
                        }
                    },
                    "400": {
                        "description": "参数错误",
                        "schema": {
                            "$ref": "#/definitions/app.Response"
                        }
                    },
                    "401": {
                        "description": "未登录",
                        "schema": {
                            "$ref": "#/definitions/app.Response"
                        }
                    }
                }
            }
        },
        "/refresh": {
            "post": {
                "description": "使用 refresh_token 刷新新的 access_token",
                "consumes": [
                    "application/json"
                ],
                "produces": [
                    "application/json"
                ],
                "tags": [
                    "用户"
                ],
                "summary": "刷新 access token",
                "parameters": [
                    {
                        "description": "刷新参数",
                        "name": "payload",
                        "in": "body",
                        "required": true,
                        "schema": {
                            "$ref": "#/definitions/handler.RefreshReq"
                        }
                    }
                ],
                "responses": {
                    "200": {
                        "description": "OK",
                        "schema": {
                            "allOf": [
                                {
                                    "$ref": "#/definitions/app.Response"
                                },
                                {
                                    "type": "object",
                                    "properties": {
                                        "data": {
                                            "$ref": "#/definitions/handler.AccessTokenResponse"
                                        }
                                    }
                                }
                            ]
                        }
                    },
                    "400": {
                        "description": "参数错误",
                        "schema": {
                            "$ref": "#/definitions/app.Response"
                        }
                    },
                    "401": {
                        "description": "token 失效",
                        "schema": {
                            "$ref": "#/definitions/app.Response"
                        }
                    }
                }
            }
        },
        "/register": {
            "post": {
                "description": "注册后返回成功提示",
                "consumes": [
                    "application/json"
                ],
                "produces": [
                    "application/json"
                ],
                "tags": [
                    "用户"
                ],
                "summary": "用户注册",
                "parameters": [
                    {
                        "description": "注册信息",
                        "name": "payload",
                        "in": "body",
                        "required": true,
                        "schema": {
                            "$ref": "#/definitions/handler.RegisterReq"
                        }
                    }
                ],
                "responses": {
                    "200": {
                        "description": "OK",
                        "schema": {
                            "allOf": [
                                {
                                    "$ref": "#/definitions/app.Response"
                                },
                                {
                                    "type": "object",
                                    "properties": {
                                        "data": {
                                            "$ref": "#/definitions/handler.MessageResponse"
                                        }
                                    }
                                }
                            ]
                        }
                    },
                    "400": {
                        "description": "参数错误",
                        "schema": {
                            "$ref": "#/definitions/app.Response"
                        }
                    }
                }
            }
        },
        "/seckill": {
            "post": {
                "security": [
                    {
                        "BearerAuth": []
                    }
                ],
                "consumes": [
                    "application/json"
                ],
                "produces": [
                    "application/json"
                ],
                "tags": [
                    "秒杀"
                ],
                "summary": "秒杀抢购",
                "parameters": [
                    {
                        "description": "秒杀参数",
                        "name": "payload",
                        "in": "body",
                        "required": true,
                        "schema": {
                            "$ref": "#/definitions/handler.SeckillReq"
                        }
                    }
                ],
                "responses": {
                    "200": {
                        "description": "OK",
                        "schema": {
                            "allOf": [
                                {
                                    "$ref": "#/definitions/app.Response"
                                },
                                {
                                    "type": "object",
                                    "properties": {
                                        "data": {
                                            "$ref": "#/definitions/handler.OrderNumResponse"
                                        }
                                    }
                                }
                            ]
                        }
                    },
                    "400": {
                        "description": "参数错误",
                        "schema": {
                            "$ref": "#/definitions/app.Response"
                        }
                    },
                    "401": {
                        "description": "未登录",
                        "schema": {
                            "$ref": "#/definitions/app.Response"
                        }
                    },
                    "429": {
                        "description": "被限流",
                        "schema": {
                            "$ref": "#/definitions/app.Response"
                        }
                    }
                }
            }
        },
        "/upload": {
            "post": {
                "security": [
                    {
                        "BearerAuth": []
                    }
                ],
                "consumes": [
                    "multipart/form-data"
                ],
                "produces": [
                    "application/json"
                ],
                "tags": [
                    "文件"
                ],
                "summary": "上传图片",
                "parameters": [
                    {
                        "type": "file",
                        "description": "图片文件",
                        "name": "file",
                        "in": "formData",
                        "required": true
                    }
                ],
                "responses": {
                    "200": {
                        "description": "OK",
                        "schema": {
                            "allOf": [
                                {
                                    "$ref": "#/definitions/app.Response"
                                },
                                {
                                    "type": "object",
                                    "properties": {
                                        "data": {
                                            "$ref": "#/definitions/handler.UploadURLResponse"
                                        }
                                    }
                                }
                            ]
                        }
                    },
                    "400": {
                        "description": "参数错误",
                        "schema": {
                            "$ref": "#/definitions/app.Response"
                        }
                    },
                    "401": {
                        "description": "未登录",
                        "schema": {
                            "$ref": "#/definitions/app.Response"
                        }
                    }
                }
            }
        },
        "/vip/profile": {
            "get": {
                "security": [
                    {
                        "BearerAuth": []
                    }
                ],
                "produces": [
                    "application/json"
                ],
                "tags": [
                    "VIP"
                ],
                "summary": "获取 VIP 信息",
                "responses": {
                    "200": {
                        "description": "OK",
                        "schema": {
                            "allOf": [
                                {
                                    "$ref": "#/definitions/app.Response"
                                },
                                {
                                    "type": "object",
                                    "properties": {
                                        "data": {
                                            "$ref": "#/definitions/service.VIPProfile"
                                        }
                                    }
                                }
                            ]
                        }
                    },
                    "401": {
                        "description": "未登录",
                        "schema": {
                            "$ref": "#/definitions/app.Response"
                        }
                    }
                }
            }
        },
        "/vip/purchase": {
            "post": {
                "security": [
                    {
                        "BearerAuth": []
                    }
                ],
                "consumes": [
                    "application/json"
                ],
                "produces": [
                    "application/json"
                ],
                "tags": [
                    "VIP"
                ],
                "summary": "购买付费 VIP",
                "parameters": [
                    {
                        "description": "付费套餐",
                        "name": "payload",
                        "in": "body",
                        "required": true,
                        "schema": {
                            "$ref": "#/definitions/handler.PurchaseVIPReq"
                        }
                    }
                ],
                "responses": {
                    "200": {
                        "description": "OK",
                        "schema": {
                            "allOf": [
                                {
                                    "$ref": "#/definitions/app.Response"
                                },
                                {
                                    "type": "object",
                                    "properties": {
                                        "data": {
                                            "$ref": "#/definitions/service.VIPProfile"
                                        }
                                    }
                                }
                            ]
                        }
                    },
                    "400": {
                        "description": "参数错误或套餐不存在",
                        "schema": {
                            "$ref": "#/definitions/app.Response"
                        }
                    },
                    "401": {
                        "description": "未登录",
                        "schema": {
                            "$ref": "#/definitions/app.Response"
                        }
                    }
                }
            }
        }
    },
    "definitions": {
        "app.Response": {
            "type": "object",
            "properties": {
                "code": {
                    "type": "integer"
                },
                "data": {},
                "msg": {
                    "type": "string"
                }
            }
        },
        "handler.AccessTokenResponse": {
            "type": "object",
            "properties": {
                "access_token": {
                    "type": "string"
                },
                "expires_in": {
                    "type": "integer"
                }
            }
        },
        "handler.CreateOrderReq": {
            "type": "object",
            "required": [
                "product_id"
            ],
            "properties": {
                "coupon_id": {
                    "type": "integer"
                },
                "product_id": {
                    "type": "integer"
                }
            }
        },
        "handler.CreateProductReq": {
            "type": "object",
            "required": [
                "name",
                "price",
                "start_time",
                "stock"
            ],
            "properties": {
                "image": {
                    "type": "string"
                },
                "name": {
                    "type": "string"
                },
                "price": {
                    "type": "number"
                },
                "start_time": {
                    "type": "string"
                },
                "stock": {
                    "type": "integer"
                }
            }
        },
        "handler.IDResponse": {
            "type": "object",
            "properties": {
                "id": {
                    "type": "integer"
                }
            }
        },
        "handler.MessageResponse": {
            "type": "object",
            "properties": {
                "message": {
                    "type": "string"
                }
            }
        },
        "handler.OrderListResponse": {
            "type": "object",
            "properties": {
                "items": {
                    "type": "array",
                    "items": {
                        "$ref": "#/definitions/model.Order"
                    }
                },
                "page": {
                    "type": "integer"
                },
                "size": {
                    "type": "integer"
                },
                "total": {
                    "type": "integer"
                }
            }
        },
        "handler.OrderNumResponse": {
            "type": "object",
            "properties": {
                "order_num": {
                    "type": "string"
                }
            }
        },
        "handler.OrderWithPaymentResponse": {
            "type": "object",
            "properties": {
                "order": {
                    "$ref": "#/definitions/model.Order"
                },
                "payment": {
                    "$ref": "#/definitions/handler.PaymentResponse"
                }
            }
        },
        "handler.PaymentCallbackReq": {
            "type": "object",
            "required": [
                "payment_id",
                "status"
            ],
            "properties": {
                "notify_data": {
                    "type": "string"
                },
                "payment_id": {
                    "type": "string"
                },
                "status": {
                    "description": "paid / failed / refunded",
                    "type": "string"
                }
            }
        },
        "handler.PaymentResponse": {
            "type": "object",
            "properties": {
                "CreatedAt": {
                    "type": "string"
                },
                "ID": {
                    "type": "integer"
                },
                "UpdatedAt": {
                    "type": "string"
                },
                "amount_cents": {
                    "type": "integer"
                },
                "notify_data": {
                    "type": "string"
                },
                "order_id": {
                    "type": "integer"
                },
                "payment_id": {
                    "type": "string"
                },
                "status": {
                    "$ref": "#/definitions/model.PaymentStatus"
                }
            }
        },
        "handler.ProductListResponse": {
            "type": "object",
            "properties": {
                "items": {
                    "type": "array",
                    "items": {
                        "$ref": "#/definitions/model.Product"
                    }
                },
                "page": {
                    "type": "integer"
                },
                "total": {
                    "type": "integer"
                }
            }
        },
        "handler.ProductListWithSizeResponse": {
            "type": "object",
            "properties": {
                "items": {
                    "type": "array",
                    "items": {
                        "$ref": "#/definitions/model.Product"
                    }
                },
                "page": {
                    "type": "integer"
                },
                "size": {
                    "type": "integer"
                },
                "total": {
                    "type": "integer"
                }
            }
        },
        "handler.PurchaseCouponReq": {
            "type": "object",
            "required": [
                "coupon_id"
            ],
            "properties": {
                "coupon_id": {
                    "type": "integer"
                }
            }
        },
        "handler.PurchaseVIPReq": {
            "type": "object",
            "required": [
                "plan_id"
            ],
            "properties": {
                "plan_id": {
                    "type": "integer"
                }
            }
        },
        "handler.RefreshReq": {
            "type": "object",
            "required": [
                "refresh_token"
            ],
            "properties": {
                "refresh_token": {
                    "type": "string"
                }
            }
        },
        "handler.RegisterReq": {
            "type": "object",
            "required": [
                "user_name",
                "user_password"
            ],
            "properties": {
                "user_name": {
                    "type": "string"
                },
                "user_password": {
                    "type": "string"
                }
            }
        },
        "handler.SeckillReq": {
            "type": "object",
            "required": [
                "product_id"
            ],
            "properties": {
                "product_id": {
                    "type": "integer"
                }
            }
        },
        "handler.TokenPairResponse": {
            "type": "object",
            "properties": {
                "access_token": {
                    "type": "string"
                },
                "expires_in": {
                    "type": "integer"
                },
                "refresh_token": {
                    "type": "string"
                }
            }
        },
        "handler.UpdateProductReq": {
            "type": "object",
            "properties": {
                "image": {
                    "type": "string"
                },
                "name": {
                    "type": "string"
                },
                "price": {
                    "type": "number"
                },
                "start_time": {
                    "type": "string"
                },
                "stock": {
                    "type": "integer"
                }
            }
        },
        "handler.UpdateProfileReq": {
            "type": "object",
            "properties": {
                "avatar": {
                    "type": "string"
                },
                "user_name": {
                    "type": "string",
                    "maxLength": 50,
                    "minLength": 1
                }
            }
        },
        "handler.UploadURLResponse": {
            "type": "object",
            "properties": {
                "url": {
                    "type": "string"
                }
            }
        },
        "handler.UserResponse": {
            "type": "object",
            "properties": {
                "CreatedAt": {
                    "type": "string"
                },
                "ID": {
                    "type": "integer"
                },
                "UpdatedAt": {
                    "type": "string"
                },
                "avatar": {
                    "type": "string"
                },
                "balance": {
                    "type": "number"
                },
                "username": {
                    "type": "string"
                }
            }
        },
        "model.CouponStatus": {
            "type": "string",
            "enum": [
                "available",
                "used",
                "expired"
            ],
            "x-enum-varnames": [
                "CouponStatusAvailable",
                "CouponStatusUsed",
                "CouponStatusExpired"
            ]
        },
        "model.CouponType": {
            "type": "string",
            "enum": [
                "full_cut",
                "discount"
            ],
            "x-enum-comments": {
                "CouponTypeDiscount": "折扣",
                "CouponTypeFullCut": "满减"
            },
            "x-enum-descriptions": [
                "满减",
                "折扣"
            ],
            "x-enum-varnames": [
                "CouponTypeFullCut",
                "CouponTypeDiscount"
            ]
        },
        "model.Order": {
            "type": "object",
            "properties": {
                "created_at": {
                    "type": "string"
                },
                "id": {
                    "type": "integer"
                },
                "order_num": {
                    "type": "string"
                },
                "product_id": {
                    "type": "integer"
                },
                "status": {
                    "$ref": "#/definitions/model.OrderStatus"
                },
                "updated_at": {
                    "type": "string"
                },
                "user_id": {
                    "type": "integer"
                }
            }
        },
        "model.OrderStatus": {
            "type": "integer",
            "enum": [
                0,
                1,
                2
            ],
            "x-enum-varnames": [
                "OrderStatusUnpaid",
                "OrderStatusPaid",
                "OrderStatusFailed"
            ]
        },
        "model.PaymentStatus": {
            "type": "string",
            "enum": [
                "pending",
                "paid",
                "failed",
                "refunded"
            ],
            "x-enum-varnames": [
                "PaymentStatusPending",
                "PaymentStatusPaid",
                "PaymentStatusFailed",
                "PaymentStatusRefunded"
            ]
        },
        "model.Product": {
            "type": "object",
            "properties": {
                "created_at": {
                    "type": "string"
                },
                "id": {
                    "type": "integer"
                },
                "image": {
                    "type": "string"
                },
                "name": {
                    "type": "string"
                },
                "price": {
                    "type": "number"
                },
                "start_time": {
                    "type": "string"
                },
                "stock": {
                    "type": "integer"
                },
                "updated_at": {
                    "type": "string"
                },
                "user_id": {
                    "type": "integer"
                }
            }
        },
        "service.MyCoupon": {
            "type": "object",
            "properties": {
                "amount_cents": {
                    "type": "integer"
                },
                "coupon_id": {
                    "type": "integer"
                },
                "description": {
                    "type": "string"
                },
                "discount_rate": {
                    "type": "integer"
                },
                "id": {
                    "type": "integer"
                },
                "min_spend_cents": {
                    "type": "integer"
                },
                "obtained_from": {
                    "type": "string"
                },
                "status": {
                    "$ref": "#/definitions/model.CouponStatus"
                },
                "title": {
                    "type": "string"
                },
                "type": {
                    "$ref": "#/definitions/model.CouponType"
                },
                "valid_from": {
                    "type": "string"
                },
                "valid_to": {
                    "type": "string"
                }
            }
        },
        "service.VIPProfile": {
            "type": "object",
            "properties": {
                "effective_level": {
                    "type": "integer"
                },
                "growth_level": {
                    "type": "integer"
                },
                "paid_expired_at": {
                    "type": "string"
                },
                "paid_level": {
                    "type": "integer"
                },
                "total_spent_cents": {
                    "type": "integer"
                }
            }
        }
    },
    "securityDefinitions": {
        "BearerAuth": {
            "type": "apiKey",
            "name": "Authorization",
            "in": "header"
        }
    }
}